CHANGES.rst
CONTRIBUTING.rst
README.md
canaille/__init__.py
canaille/commands.py
canaille/app/__init__.py
canaille/app/commands.py
canaille/app/configuration.py
canaille/app/features.py
canaille/app/flask.py
canaille/app/forms.py
canaille/app/i18n.py
canaille/app/installation.py
canaille/app/logging.py
canaille/app/mails.py
canaille/app/mails_sending_conditions.py
canaille/app/models.py
canaille/app/otp.py
canaille/app/security.py
canaille/app/sentry.py
canaille/app/session.py
canaille/app/sms.py
canaille/app/templating.py
canaille/app/toml.py
canaille/backends/__init__.py
canaille/backends/commands.py
canaille/backends/models.py
canaille/backends/ldap/__init__.py
canaille/backends/ldap/backend.py
canaille/backends/ldap/configuration.py
canaille/backends/ldap/ldapobject.py
canaille/backends/ldap/ldapobjectquery.py
canaille/backends/ldap/utils.py
canaille/backends/ldap/models/__init__.py
canaille/backends/ldap/models/core.py
canaille/backends/ldap/models/oidc.py
canaille/backends/ldap/schemas/oauth2-openldap.ldif
canaille/backends/ldap/schemas/oauth2-openldap.schema
canaille/backends/memory/__init__.py
canaille/backends/memory/backend.py
canaille/backends/memory/models/__init__.py
canaille/backends/memory/models/core.py
canaille/backends/memory/models/oidc.py
canaille/backends/sql/__init__.py
canaille/backends/sql/backend.py
canaille/backends/sql/configuration.py
canaille/backends/sql/utils.py
canaille/backends/sql/migrations/1736443094_init.py
canaille/backends/sql/migrations/1736443538_0_0_58.py
canaille/backends/sql/migrations/1738929510_client_jwk_has_been_renamed_jwks.py
canaille/backends/sql/migrations/1740765703_rename_client_preconsent_in_client_.py
canaille/backends/sql/migrations/1742033764_ordered_relationships.py
canaille/backends/sql/migrations/1742298790_missing_oidc_client_attributes.py
canaille/backends/sql/migrations/1743675164_add_login_metadata_to_authorizationcode.py
canaille-0.1.0.dist-info/METADATA
canaille-0.1.0.dist-info/WHEEL
canaille-0.1.0.dist-info/entry_points.txt
canaille-0.1.0.dist-info/licenses/LICENSE.rst
canaille-0.1.0.dist-info/RECORD
