Metadata-Version: 2.4
Name: Canaille
Version: 0.1.0
Summary: Lightweight identity and authorization management software
Project-URL: homepage, https://canaille.yaal.coop
Project-URL: documentation, https://canaille.readthedocs.io/en/latest/
Project-URL: repository, https://gitlab.com/yaal/canaille
Author-email: Yaal Coop <contact@yaal.coop>
Maintainer-email: Éloi Rivard <eloi@yaal.coop>
License: Copyright (c) 2020-2023 by Yaal Coop
License-File: LICENSE.rst
Keywords: authentication,identity,oauth,oauth2,oidc,openid
Classifier: Development Status :: 4 - Beta
Classifier: Environment :: Web Environment
Classifier: Intended Audience :: Developers
Classifier: License :: OSI Approved :: MIT License
Classifier: Operating System :: OS Independent
Classifier: Programming Language :: Python
Classifier: Programming Language :: Python :: 3.10
Classifier: Programming Language :: Python :: 3.11
Classifier: Programming Language :: Python :: 3.12
Classifier: Programming Language :: Python :: 3.13
Classifier: Programming Language :: Python :: Implementation :: CPython
Classifier: Topic :: System :: Systems Administration :: Authentication/Directory
Classifier: Topic :: System :: Systems Administration :: Authentication/Directory :: LDAP
Requires-Python: >=3.10
Requires-Dist: blinker>=1.9.0
Requires-Dist: click>=8.2.0
Requires-Dist: dramatiq-eager-broker>=0.1.0
Requires-Dist: dramatiq>=1.18.0
Requires-Dist: flask-caching>=2.3.0
Requires-Dist: flask-dramatiq>=0.6.0
Requires-Dist: flask-wtf>=1.2.1
Requires-Dist: flask>=3.0.0
Requires-Dist: httpx>=0.28.1
Requires-Dist: pika>=1.3.2
Requires-Dist: pydantic-settings>=2.8.0
Requires-Dist: wtforms>=3.1.1
Provides-Extra: front
Requires-Dist: email-validator>=2.0.0; extra == 'front'
Requires-Dist: flask-babel>=4.0.0; extra == 'front'
Requires-Dist: flask-talisman>=1.1.0; extra == 'front'
Requires-Dist: flask-themer>=2.0.0; extra == 'front'
Requires-Dist: isodate>=0.7.2; extra == 'front'
Requires-Dist: pycountry>=23.12.7; extra == 'front'
Requires-Dist: pytz>=2022.7; extra == 'front'
Requires-Dist: tomlkit>=0.13.2; extra == 'front'
Requires-Dist: zxcvbn-rs-py>=0.2.0; extra == 'front'
Provides-Extra: ldap
Requires-Dist: python-ldap>=3.4.4; extra == 'ldap'
Provides-Extra: mysql
Requires-Dist: flask-alembic>=3.1.1; extra == 'mysql'
Requires-Dist: passlib>=1.7.4; extra == 'mysql'
Requires-Dist: sqlalchemy-json>=0.7.0; extra == 'mysql'
Requires-Dist: sqlalchemy-utils>=0.41.1; extra == 'mysql'
Requires-Dist: sqlalchemy[pymysql]>=2.0.23; extra == 'mysql'
Provides-Extra: oidc
Requires-Dist: authlib>=1.6.5; extra == 'oidc'
Requires-Dist: joserfc>=1.4.0; extra == 'oidc'
Provides-Extra: otp
Requires-Dist: otpauth>=2.2.1; extra == 'otp'
Requires-Dist: pillow>=11.0.0; extra == 'otp'
Requires-Dist: qrcode>=8.0; extra == 'otp'
Provides-Extra: postgresql
Requires-Dist: flask-alembic>=3.1.1; extra == 'postgresql'
Requires-Dist: passlib>=1.7.4; extra == 'postgresql'
Requires-Dist: sqlalchemy-json>=0.7.0; extra == 'postgresql'
Requires-Dist: sqlalchemy-utils>=0.41.1; extra == 'postgresql'
Requires-Dist: sqlalchemy[postgresql-psycopg2binary]>=2.0.23; extra == 'postgresql'
Provides-Extra: rabbitmq
Requires-Dist: dramatiq[redis]>=1.18.0; extra == 'rabbitmq'
Provides-Extra: redis
Requires-Dist: dramatiq[redis]>=1.18.0; extra == 'redis'
Provides-Extra: scim
Requires-Dist: authlib>=1.5.1; extra == 'scim'
Requires-Dist: httpx>=0.28.1; extra == 'scim'
Requires-Dist: scim2-client>=0.5.1; extra == 'scim'
Requires-Dist: scim2-models>=0.4.0; extra == 'scim'
Provides-Extra: sentry
Requires-Dist: sentry-sdk>=2.0.0; extra == 'sentry'
Provides-Extra: server
Requires-Dist: asgiref>=3.9.2; extra == 'server'
Requires-Dist: hypercorn>=0.17.3; extra == 'server'
Requires-Dist: isodate>=0.7.2; extra == 'server'
Requires-Dist: pydanclick>=0.5.0; extra == 'server'
Requires-Dist: tomlkit>=0.13.2; extra == 'server'
Provides-Extra: sms
Requires-Dist: smpplib>=2.2.3; extra == 'sms'
Provides-Extra: sqlite
Requires-Dist: flask-alembic>=3.1.1; extra == 'sqlite'
Requires-Dist: passlib>=1.7.4; extra == 'sqlite'
Requires-Dist: sqlalchemy-json>=0.7.0; extra == 'sqlite'
Requires-Dist: sqlalchemy-utils>=0.41.1; extra == 'sqlite'
Requires-Dist: sqlalchemy>=2.0.23; extra == 'sqlite'
